umlars_translator/__init__.py
umlars_translator/__main__.py
umlars_translator/app/__init__.py
umlars_translator/app/adapters/__init__.py
umlars_translator/app/adapters/apis/__init__.py
umlars_translator/app/adapters/apis/api_connector.py
umlars_translator/app/adapters/apis/bootstrap.py
umlars_translator/app/adapters/apis/config.py
umlars_translator/app/adapters/apis/rest_api_connector.py
umlars_translator/app/adapters/bootstrap.py
umlars_translator/app/adapters/message_brokers/__init__.py
umlars_translator/app/adapters/message_brokers/bootstrap.py
umlars_translator/app/adapters/message_brokers/config.py
umlars_translator/app/adapters/message_brokers/message_consumer.py
umlars_translator/app/adapters/message_brokers/message_producer.py
umlars_translator/app/adapters/message_brokers/rabbitmq_message_consumer.py
umlars_translator/app/adapters/message_brokers/rabbitmq_message_producer.py
umlars_translator/app/adapters/repositories/mongo_uml_model_repository.py
umlars_translator/app/adapters/repositories/uml_model_repository.py
umlars_translator/app/config.py
umlars_translator/app/dtos/input.py
umlars_translator/app/dtos/messages.py
umlars_translator/app/dtos/uml_model.py
umlars_translator/app/exceptions.py
umlars_translator/app/main.py
umlars_translator/app/services/models_translator.py
umlars_translator/app/utils/__init__.py
umlars_translator/app/utils/functions.py
umlars_translator/bootstrap.py
umlars_translator/cli/__init__.py
umlars_translator/cli/cli_manager.py
umlars_translator/config.py
umlars_translator/core/__init__.py
umlars_translator/core/bootstrap.py
umlars_translator/core/config.py
umlars_translator/core/configuration/__init__.py
umlars_translator/core/configuration/config_namespace.py
umlars_translator/core/configuration/config_proxy.py
umlars_translator/core/deserialization/README.md
umlars_translator/core/deserialization/__init__.py
umlars_translator/core/deserialization/abstract/__init__.py
umlars_translator-0.0.6.dist-info/LICENSE
umlars_translator-0.0.6.dist-info/METADATA
umlars_translator-0.0.6.dist-info/WHEEL
umlars_translator-0.0.6.dist-info/entry_points.txt
umlars_translator-0.0.6.dist-info/RECORD
