Metadata-Version: 2.3
Name: umlars_translator
Version: 0.0.6
Summary: UML representation and analysis system - translation service
License: MIT
Keywords: UML,deserializer,serializer
Author: Filip Pawłowski
Author-email: filip.pawlowski001@gmail.com
Requires-Python: >=3.10,<4.0
Classifier: Development Status :: 3 - Alpha
Classifier: Intended Audience :: Developers
Classifier: Intended Audience :: Education
Classifier: Intended Audience :: Science/Research
Classifier: License :: OSI Approved :: MIT License
Classifier: Operating System :: OS Independent
Classifier: Programming Language :: Python :: 3
Classifier: Programming Language :: Python :: 3.10
Classifier: Programming Language :: Python :: 3.11
Classifier: Programming Language :: Python :: 3.12
Classifier: Programming Language :: Python :: 3.13
Classifier: Topic :: Documentation
Classifier: Topic :: Scientific/Engineering
Classifier: Topic :: Software Development
Requires-Dist: aio-pika (>=9.4.2,<10.0.0)
Requires-Dist: aiohttp (>=3.9.5,<4.0.0)
Requires-Dist: fastapi (>=0.111.1,<0.112.0)
Requires-Dist: kink (>=0.8.0,<0.9.0)
Requires-Dist: motor (>=3.5.1,<4.0.0)
Requires-Dist: pydantic (>=2.7.4,<3.0.0)
Requires-Dist: uvicorn[standard] (>=0.30.1,<0.31.0)
Requires-Dist: watchfiles (==0.21.0)
Project-URL: Backend, https://github.com/UMLI-Organization/umlars-backend
Project-URL: Issues, https://github.com/UMLI-Organization/umlars-translator/issues
Project-URL: Repository, https://github.com/UMLI-Organization/umlars-translator
